nasa_admin_cli/__init__.py
nasa_admin_cli/main.py
nasa_admin_cli/missions.json
nasa_admin_cli/users.json
nasa_admin_cli-0.1.7.dist-info/METADATA
nasa_admin_cli-0.1.7.dist-info/WHEEL
nasa_admin_cli-0.1.7.dist-info/entry_points.txt
nasa_admin_cli-0.1.7.dist-info/top_level.txt
nasa_admin_cli-0.1.7.dist-info/RECORD
