Metadata-Version: 2.4
Name: nasa-admin-cli
Version: 0.1.7
Summary: NASA Admin CLI tool — cross-platform login system
Home-page: https://github.com/yourusername/nasa-admin-cli
Author: Ashlesh Deshmukh
Author-email: youremail@example.com
License: MIT
Requires-Python: >=3.8
Requires-Dist: pwinput
Dynamic: author-email
Dynamic: home-page
Dynamic: requires-python
